golean/__init__.py
golean/client.py
golean/example_usage.py
golean-0.2.4.dist-info/METADATA
golean-0.2.4.dist-info/WHEEL
golean-0.2.4.dist-info/top_level.txt
golean-0.2.4.dist-info/RECORD
