Metadata-Version: 2.1
Name: golean
Version: 0.2.4
Summary: A Python package for interacting with the GoLean API service.
Home-page: https://golean.ai
Author: Connor Peng
Author-email: jinghong.peng@golean.ai
Classifier: Programming Language :: Python :: 3
Classifier: Operating System :: OS Independent
Classifier: Development Status :: 3 - Alpha
Classifier: Intended Audience :: Developers
Classifier: Topic :: Software Development :: Libraries
Requires-Python: >=3.6
Requires-Dist: requests
Requires-Dist: python-dotenv
Requires-Dist: tiktoken
